NeutronImaging-1.2.data/scripts/generate_config.py
NeutronImaging-1.2.data/scripts/mcp_detector_correction.py
neutronimaging/__init__.py
neutronimaging/_version.py
neutronimaging/detector_correction.py
neutronimaging/npmath.py
neutronimaging/preprocess.py
neutronimaging/util.py
NeutronImaging-1.2.dist-info/LICENSE
NeutronImaging-1.2.dist-info/METADATA
NeutronImaging-1.2.dist-info/WHEEL
NeutronImaging-1.2.dist-info/top_level.txt
NeutronImaging-1.2.dist-info/RECORD
