Metadata-Version: 2.1
Name: NeutronImaging
Version: 1.2
Summary: Neutron Imaging Reduction
Home-page: https://code.ornl.gov/sns-hfir-scse/imaging/neutronimaging
Author: C.Zhang
Author-email: zhangc@ornl.gov
Maintainer: C.Zhang
Maintainer-email: zhangc@ornl.gov
License: BSD
Keywords: neutron imaging mcp
Platform: UNKNOWN
Classifier: Development Status :: 5 - Production/Stable
Classifier: Intended Audience :: Developers
Classifier: Natural Language :: English
Classifier: License :: OSI Approved :: GNU Lesser General Public License v2 (LGPLv2)
Classifier: Operating System :: OS Independent
Classifier: Programming Language :: Python
Classifier: Programming Language :: Python :: 3
Classifier: Programming Language :: Python :: 3.5
Classifier: Programming Language :: Python :: 3.6
Classifier: Programming Language :: Python :: 3.7
Classifier: Programming Language :: Python :: 3.8
Classifier: Programming Language :: Python :: Implementation :: CPython
Classifier: Programming Language :: Python :: Implementation :: PyPy
Classifier: Topic :: Software Development :: Libraries :: Python Modules
Requires-Dist: docopt
Requires-Dist: ipympl
Requires-Dist: matplotlib
Requires-Dist: numpy
Requires-Dist: NeuNorm
Requires-Dist: pandas
Requires-Dist: tqdm
